eidos/__init__.py
eidos/styles.py
eidos/tags.py
eidos/utils.py
eidos/components/__init__.py
eidos/components/feedback.py
eidos/components/headers.py
eidos/components/navigation.py
eidos/components/table.py
eidos/components/tabs.py
eidos/components/theme.py
eidos/css/styles.css
eidos/css/themes/dark.css
eidos/css/themes/eidos-variables.css
eidos/css/themes/light.css
eidos/js/eidos.js
eidos/js/theme.js
eidos/plugins/__init__.py
eidos/plugins/markdown/__init__.py
eidos/plugins/markdown/components.py
eidos/plugins/markdown/renderer.py
eidos/plugins/markdown/css/markdown.css
eidos/plugins/markdown/extensions/__init__.py
eidos/plugins/markdown/extensions/alerts.py
eidosui-0.12.3.dist-info/METADATA
eidosui-0.12.3.dist-info/WHEEL
eidosui-0.12.3.dist-info/licenses/LICENSE
eidosui-0.12.3.dist-info/RECORD
