Metadata-Version: 2.4
Name: eidosui
Version: 0.12.3
Summary: A modern, Tailwind CSS-based UI library for air development
Project-URL: Homepage, https://github.com/isaac-flath/EidosUI
Project-URL: Repository, https://github.com/isaac-flath/EidosUI
Project-URL: Issues, https://github.com/isaac-flath/EidosUI/issues
Project-URL: Documentation, https://github.com/isaac-flath/EidosUI#readme
Author: Isaac Flath
License-Expression: MIT
License-File: LICENSE
Keywords: air,components,css,fastapi,tailwind,ui,web
Classifier: Development Status :: 3 - Alpha
Classifier: Intended Audience :: Developers
Classifier: License :: OSI Approved :: MIT License
Classifier: Topic :: Internet :: WWW/HTTP :: Dynamic Content
Classifier: Topic :: Software Development :: Libraries :: Python Modules
Requires-Python: >=3.13
Requires-Dist: air>=0.4.0
Requires-Dist: airpine>=0.2.1
Requires-Dist: fastapi[standard]
Requires-Dist: uvicorn
Provides-Extra: dev
Requires-Dist: black; extra == 'dev'
Requires-Dist: isort; extra == 'dev'
Requires-Dist: mypy; extra == 'dev'
Requires-Dist: pytest; extra == 'dev'
Requires-Dist: ruff; extra == 'dev'
Provides-Extra: markdown
Requires-Dist: markdown>=3.10; extra == 'markdown'
